AUTHORS
ChangeLog
LICENSE
MANIFEST.in
README.rst
setup.cfg
setup.py
leonardo_theme_adminlte/__init__.py
leonardo_theme_adminlte.egg-info/PKG-INFO
leonardo_theme_adminlte.egg-info/SOURCES.txt
leonardo_theme_adminlte.egg-info/dependency_links.txt
leonardo_theme_adminlte.egg-info/not-zip-safe
leonardo_theme_adminlte.egg-info/pbr.json
leonardo_theme_adminlte.egg-info/top_level.txt
leonardo_theme_adminlte/static/base/page/adminlte/adminlte.css
leonardo_theme_adminlte/static/base/page/adminlte/skins/black-light.css
leonardo_theme_adminlte/static/base/page/adminlte/skins/black.css
leonardo_theme_adminlte/static/base/page/adminlte/skins/blue-light.css
leonardo_theme_adminlte/static/base/page/adminlte/skins/blue.css
leonardo_theme_adminlte/static/base/page/adminlte/skins/green-light.css
leonardo_theme_adminlte/static/base/page/adminlte/skins/green.css
leonardo_theme_adminlte/static/base/page/adminlte/skins/purple-light.css
leonardo_theme_adminlte/static/base/page/adminlte/skins/purple.css
leonardo_theme_adminlte/static/base/page/adminlte/skins/red-light.css
leonardo_theme_adminlte/static/base/page/adminlte/skins/red.css
leonardo_theme_adminlte/static/base/page/adminlte/skins/yellow-light.css
leonardo_theme_adminlte/static/base/page/adminlte/skins/yellow.css
leonardo_theme_adminlte/templates/base/page/adminlte.html